buffpy/__init__.py
buffpy/api.py
buffpy/exceptions.py
buffpy/response.py
buffpy/managers/__init__.py
buffpy/managers/profiles.py
buffpy/managers/updates.py
buffpy/models/__init__.py
buffpy/models/link.py
buffpy/models/profile.py
buffpy/models/update.py
buffpy/models/user.py
buffpy-3.1.1.dist-info/LICENSE.txt
buffpy-3.1.1.dist-info/METADATA
buffpy-3.1.1.dist-info/WHEEL
buffpy-3.1.1.dist-info/top_level.txt
buffpy-3.1.1.dist-info/RECORD
