Metadata-Version: 2.1
Name: buffpy
Version: 3.1.1
Summary: Python library for Buffer App
Home-page: https://github.com/vtemian/buffpy
Author: Vlad Temian
Author-email: vladtemian@gmail.com
License: UNKNOWN
Platform: any
Classifier: Programming Language :: Python :: 3.6
Classifier: Programming Language :: Python :: 3.7
Requires-Dist: certifi (==2019.3.9)
Requires-Dist: chardet (==3.0.4)
Requires-Dist: colorama (==0.4.1)
Requires-Dist: coverage (==4.5.3)
Requires-Dist: httpretty (==0.9.6)
Requires-Dist: idna (==2.8)
Requires-Dist: rauth (==0.7.3)
Requires-Dist: requests (==2.22.0)
Requires-Dist: six (==1.12.0)
Requires-Dist: urllib3 (==1.25.2)
